LICENSE.txt
MANIFEST.in
setup.cfg
setup.py
BootstrapPy.egg-info/PKG-INFO
BootstrapPy.egg-info/SOURCES.txt
BootstrapPy.egg-info/dependency_links.txt
BootstrapPy.egg-info/entry_points.txt
BootstrapPy.egg-info/not-zip-safe
BootstrapPy.egg-info/requires.txt
BootstrapPy.egg-info/top_level.txt
bootstrappy/__init__.py
bootstrappy/application.py
bootstrappy/configuration.py
bootstrappy/decorators.py
bootstrappy/logger.py
bootstrappy/middleware.py
bootstrappy/router.py
bootstrappy/tmplt.py
bootstrappy/util.py
bootstrappy/templates/MANIFEST.in
bootstrappy/templates/__init__.py
bootstrappy/templates/development.ini_tmpl
bootstrappy/templates/setup.cfg_tmpl
bootstrappy/templates/setup.py_tmpl
bootstrappy/templates/+package+/__init__.py
bootstrappy/templates/+package+/application/__init__.py_tmpl
bootstrappy/templates/+package+/application/configuration.py_tmpl
bootstrappy/templates/+package+/application/route_map.py_tmpl
bootstrappy/templates/+package+/controllers/__init__.py
bootstrappy/templates/+package+/controllers/api.py_tmpl
bootstrappy/templates/+package+/controllers/auth.py_tmpl
bootstrappy/templates/+package+/controllers/base.py_tmpl
bootstrappy/templates/+package+/controllers/root.py_tmpl
bootstrappy/templates/+package+/lib/__init__.py
bootstrappy/templates/+package+/lib/app_globals.py_tmpl
bootstrappy/templates/+package+/lib/forms.py_tmpl
bootstrappy/templates/+package+/lib/helpers.py
bootstrappy/templates/+package+/model/__init__.py_tmpl
bootstrappy/templates/+package+/model/base.py_tmpl
bootstrappy/templates/+package+/model/core.py_tmpl
bootstrappy/templates/+package+/model/mapping.py_tmpl
bootstrappy/templates/+package+/model/util.py_tmpl
bootstrappy/templates/+package+/static/test.html_tmpl
bootstrappy/templates/+package+/static/css/bootstrap-responsive.css
bootstrappy/templates/+package+/static/css/bootstrap-responsive.min.css
bootstrappy/templates/+package+/static/css/bootstrap-wizard.css
bootstrappy/templates/+package+/static/css/bootstrap.css
bootstrappy/templates/+package+/static/css/bootstrap.min.css
bootstrappy/templates/+package+/static/css/ellipsis-xbl.xml
bootstrappy/templates/+package+/static/css/glyphicons.css
bootstrappy/templates/+package+/static/css/jquery.gritter.css
