Metadata-Version: 1.0
Name: BootstrapPy
Version: 0.6
Summary: A Python web framework with Twitter's Bootstrap.
Home-page: http://www.bootstrappy.org
Author: Noel Morgan
Author-email: noel@bootstrappy.org
License: MPL 2.0
Keywords: python web framework bootstrap sqlalchemy knockout jquery bootstrappy
Platform: UNKNOWN
Classifier: Environment :: Web Environment
